graphite/__init__.py
graphitedb-0.1.3.dist-info/licenses/LICENSE
graphitedb-0.1.3.dist-info/METADATA
graphitedb-0.1.3.dist-info/WHEEL
graphitedb-0.1.3.dist-info/top_level.txt
graphitedb-0.1.3.dist-info/RECORD
