Metadata-Version: 2.4
Name: graphitedb
Version: 0.1.3
Summary: A clean, embedded graph database engine for Python.
Author-email: Mahan Khalili <khalili1388mahan@gmail.com>
Maintainer-email: Mahan Khalili <khalili1388mahan@gmail.com>
License-Expression: MIT
Project-URL: Homepage, https://github.com/mkh-user/graphite
Project-URL: Issues, https://github.com/mkh-user/graphite/issues
Classifier: Programming Language :: Python :: 3
Classifier: Operating System :: OS Independent
Requires-Python: >=3.9
License-File: LICENSE
Dynamic: license-file
